jvrc_description/__init__.py
jvrc_description/meshes/L_ANKLE_P_S.dae
jvrc_description/meshes/L_ELBOW_P_S.dae
jvrc_description/meshes/L_ELBOW_Y_S.dae
jvrc_description/meshes/L_HIP_R_S.dae
jvrc_description/meshes/L_HIP_Y_S.dae
jvrc_description/meshes/L_KNEE_S.dae
jvrc_description/meshes/L_LINDEX_S.dae
jvrc_description/meshes/L_LLITTLE_S.dae
jvrc_description/meshes/L_LTHUMB_S.dae
jvrc_description/meshes/L_SHOULDER_P_S.dae
jvrc_description/meshes/L_SHOULDER_Y_S.dae
jvrc_description/meshes/L_UINDEX_S.dae
jvrc_description/meshes/L_ULITTLE_S.dae
jvrc_description/meshes/L_UTHUMB_S.dae
jvrc_description/meshes/L_WRIST_Y_S.dae
jvrc_description/meshes/Map01_siri.jpg
jvrc_description/meshes/Map03_douF.jpg
jvrc_description/meshes/Map03_douR.jpg
jvrc_description/meshes/Map05_atamaF.jpg
jvrc_description/meshes/Map05_atamaR.jpg
jvrc_description/meshes/Map06_migikata.jpg
jvrc_description/meshes/Map07_migijowan.jpg
jvrc_description/meshes/Map08_migikawan.jpg
jvrc_description/meshes/Map09_migitekubi.jpg
jvrc_description/meshes/Map10_migitenohira.jpg
jvrc_description/meshes/Map12_migiisshisaki.jpg
jvrc_description/meshes/Map14_miginishisaki.jpg
jvrc_description/meshes/Map28_migimata.jpg
jvrc_description/meshes/Map29_migidaitai.jpg
jvrc_description/meshes/Map30_migisune.jpg
jvrc_description/meshes/Map31_migiashikubi.jpg
jvrc_description/meshes/Map32_migiashi.jpg
jvrc_description/meshes/NECK_P_S.dae
jvrc_description/meshes/NECK_Y_S.dae
jvrc_description/meshes/PELVIS_S.dae
jvrc_description/meshes/R_ANKLE_P_S.dae
jvrc_description/meshes/R_ELBOW_P_S.dae
jvrc_description/meshes/R_ELBOW_Y_S.dae
jvrc_description/meshes/R_HIP_R_S.dae
jvrc_description/meshes/R_HIP_Y_S.dae
jvrc_description/meshes/R_KNEE_S.dae
jvrc_description/meshes/R_LINDEX_S.dae
jvrc_description/meshes/R_LLITTLE_S.dae
jvrc_description/meshes/R_LTHUMB_S.dae
jvrc_description/meshes/R_SHOULDER_P_S.dae
jvrc_description/meshes/R_SHOULDER_Y_S.dae
jvrc_description/meshes/R_UINDEX_S.dae
jvrc_description/meshes/R_ULITTLE_S.dae
jvrc_description-1.1.1.dist-info/WHEEL
jvrc_description-1.1.1.dist-info/METADATA
jvrc_description-1.1.1.dist-info/RECORD
