Metadata-Version: 2.1
Name: jvrc_description
Version: 1.1.1
Summary: URDF description of the JVRC humanoid model.
Author-email: Stéphane Caron <stephane.caron@normalesup.org>
Maintainer-email: Stéphane Caron <stephane.caron@normalesup.org>
Requires-Python: >=3.7
Classifier: Development Status :: 5 - Production/Stable
Classifier: Intended Audience :: Developers
Classifier: Intended Audience :: Science/Research
Classifier: License :: OSI Approved :: Apache Software License
Classifier: Operating System :: OS Independent
Classifier: Programming Language :: Python :: 3
Classifier: Programming Language :: Python :: 3.10
Classifier: Programming Language :: Python :: 3.7
Classifier: Programming Language :: Python :: 3.8
Classifier: Programming Language :: Python :: 3.9
Classifier: Topic :: Scientific/Engineering :: Mathematics
Classifier: Topic :: Scientific/Engineering :: Physics
Project-URL: Changelog, https://github.com/stephane-caron/jvrc_description/blob/master/CHANGELOG.md
Project-URL: Source, https://github.com/stephane-caron/jvrc_description
Project-URL: Tracker, https://github.com/stephane-caron/jvrc_description/issues
